sgb_advisor/__init__.py
sgb_advisor/__main__.py
sgb_advisor/assets/sample_data.json
sgb_advisor/assets/scrips.csv
sgb_advisor/assets/telegram_template.svg
sgb_advisor/assets/template.html
sgb_advisor/data.py
sgb_advisor/logg.py
sgb_advisor/models.py
sgb_advisor/notify/__init__.py
sgb_advisor/notify/common.py
sgb_advisor/notify/email_sender.py
sgb_advisor/notify/py.typed
sgb_advisor/notify/teleg.py
sgb_advisor/py.typed
sgb_advisor/quick_mafs.py
sgb_advisor-0.2.4.dist-info/WHEEL
sgb_advisor-0.2.4.dist-info/entry_points.txt
sgb_advisor-0.2.4.dist-info/METADATA
sgb_advisor-0.2.4.dist-info/RECORD
