Metadata-Version: 2.4
Name: sgb-advisor
Version: 0.2.4
Summary: A tool to analyse Sovereign Gold Bonds and compare their yields.
Keywords: sovereign-gold-bonds,sgb,india-finance,finance
Author: Vishal Nandagopal
Author-email: Vishal Nandagopal <dev@vishalnandagopal.com>
License-Expression: GPL-3.0-only
Requires-Dist: loguru>=0.7.3
Requires-Dist: python-dotenv>=1.2.1
Requires-Dist: pyxirr>=0.10.8
Requires-Dist: requests>=2.32.5
Requires-Dist: boto3>=1.40.74
Requires-Dist: playwright>=1.56.0
Requires-Python: >=3.10
Project-URL: documentation, https://github.com/vishalnandagopal/sgb-advisor/blob/master/README.md#running-the-app
Project-URL: homepage, https://github.com/vishalnandagopal/sgb-advisor
Project-URL: issues, https://github.com/vishalnandagopal/sgb-advisor/issues
Project-URL: source, https://github.com/vishalnandagopal/sgb-advisor.git
